Compiled from "Polymorphic.java"
public class ind.lw.java.concept.polymorphic.Polymorphic {
  public ind.lw.java.concept.polymorphic.Polymorphic();
    Code:
       0: aload_0
       1: invokespecial #1                  // Method java/lang/Object."<init>":()V
       4: return

  public static void main(java.lang.String[]);
    Code:
       0: new           #2                  // class ind/lw/java/concept/polymorphic/A
       3: dup
       4: invokespecial #3                  // Method ind/lw/java/concept/polymorphic/A."<init>":()V
       7: astore_1
       8: new           #4                  // class ind/lw/java/concept/polymorphic/B
      11: dup
      12: invokespecial #5                  // Method ind/lw/java/concept/polymorphic/B."<init>":()V
      15: astore_2
      16: new           #4                  // class ind/lw/java/concept/polymorphic/B
      19: dup
      20: invokespecial #5                  // Method ind/lw/java/concept/polymorphic/B."<init>":()V
      23: astore_3
      24: new           #6                  // class ind/lw/java/concept/polymorphic/C
      27: dup
      28: invokespecial #7                  // Method ind/lw/java/concept/polymorphic/C."<init>":()V
      31: astore        4
      33: new           #8                  // class ind/lw/java/concept/polymorphic/D
      36: dup
      37: invokespecial #9                  // Method ind/lw/java/concept/polymorphic/D."<init>":()V
      40: astore        5
      42: getstatic     #10                 // Field java/lang/System.out:Ljava/io/PrintStream;
      45: aload_1
      46: aload_2
      47: invokevirtual #11                 // Method ind/lw/java/concept/polymorphic/A.show:(Lind/lw/java/concept/polymorphic/A;)Ljava/lang/String;
      50: invokevirtual #12                 // Method java/io/PrintStream.println:(Ljava/lang/String;)V
      53: getstatic     #10                 // Field java/lang/System.out:Ljava/io/PrintStream;
      56: aload_1
      57: aload_3
      58: invokevirtual #11                 // Method ind/lw/java/concept/polymorphic/A.show:(Lind/lw/java/concept/polymorphic/A;)Ljava/lang/String;
      61: invokevirtual #12                 // Method java/io/PrintStream.println:(Ljava/lang/String;)V
      64: getstatic     #10                 // Field java/lang/System.out:Ljava/io/PrintStream;
      67: aload_1
      68: aload         4
      70: invokevirtual #11                 // Method ind/lw/java/concept/polymorphic/A.show:(Lind/lw/java/concept/polymorphic/A;)Ljava/lang/String;
      73: invokevirtual #12                 // Method java/io/PrintStream.println:(Ljava/lang/String;)V
      76: getstatic     #10                 // Field java/lang/System.out:Ljava/io/PrintStream;
      79: aload_1
      80: aload         5
      82: invokevirtual #13                 // Method ind/lw/java/concept/polymorphic/A.show:(Lind/lw/java/concept/polymorphic/D;)Ljava/lang/String;
      85: invokevirtual #12                 // Method java/io/PrintStream.println:(Ljava/lang/String;)V
      88: getstatic     #10                 // Field java/lang/System.out:Ljava/io/PrintStream;
      91: aload_2
      92: aload_3
      93: invokevirtual #11                 // Method ind/lw/java/concept/polymorphic/A.show:(Lind/lw/java/concept/polymorphic/A;)Ljava/lang/String;
      96: invokevirtual #12                 // Method java/io/PrintStream.println:(Ljava/lang/String;)V
      99: getstatic     #10                 // Field java/lang/System.out:Ljava/io/PrintStream;
     102: aload_2
     103: aload         4
     105: invokevirtual #11                 // Method ind/lw/java/concept/polymorphic/A.show:(Lind/lw/java/concept/polymorphic/A;)Ljava/lang/String;
     108: invokevirtual #12                 // Method java/io/PrintStream.println:(Ljava/lang/String;)V
     111: getstatic     #10                 // Field java/lang/System.out:Ljava/io/PrintStream;
     114: aload_2
     115: aload         5
     117: invokevirtual #13                 // Method ind/lw/java/concept/polymorphic/A.show:(Lind/lw/java/concept/polymorphic/D;)Ljava/lang/String;
     120: invokevirtual #12                 // Method java/io/PrintStream.println:(Ljava/lang/String;)V
     123: getstatic     #10                 // Field java/lang/System.out:Ljava/io/PrintStream;
     126: aload_3
     127: aload_3
     128: invokevirtual #14                 // Method ind/lw/java/concept/polymorphic/B.show:(Lind/lw/java/concept/polymorphic/B;)Ljava/lang/String;
     131: invokevirtual #12                 // Method java/io/PrintStream.println:(Ljava/lang/String;)V
     134: getstatic     #10                 // Field java/lang/System.out:Ljava/io/PrintStream;
     137: aload_3
     138: aload         4
     140: invokevirtual #14                 // Method ind/lw/java/concept/polymorphic/B.show:(Lind/lw/java/concept/polymorphic/B;)Ljava/lang/String;
     143: invokevirtual #12                 // Method java/io/PrintStream.println:(Ljava/lang/String;)V
     146: getstatic     #10                 // Field java/lang/System.out:Ljava/io/PrintStream;
     149: aload_3
     150: aload         5
     152: invokevirtual #15                 // Method ind/lw/java/concept/polymorphic/B.show:(Lind/lw/java/concept/polymorphic/D;)Ljava/lang/String;
     155: invokevirtual #12                 // Method java/io/PrintStream.println:(Ljava/lang/String;)V
     158: return
}
