Compiled from "TargetProxy.java"
public class ind.lw.java.dynamicproxy.TargetProxy implements java.lang.reflect.InvocationHandler {
  public java.lang.Object invoke(java.lang.Object, java.lang.reflect.Method, java.lang.Object[]) throws java.lang.Throwable;
    Code:
       0: getstatic     #1                  // Field java/lang/System.out:Ljava/io/PrintStream;
       3: ldc           #2                  // String before
       5: invokevirtual #3                  // Method java/io/PrintStream.println:(Ljava/lang/String;)V
       8: aload_2
       9: aload_0
      10: getfield      #4                  // Field target:Ljava/lang/Object;
      13: aload_3
      14: invokevirtual #5                  // Method java/lang/reflect/Method.invoke:(Ljava/lang/Object;[Ljava/lang/Object;)Ljava/lang/Object;
      17: astore        4
      19: getstatic     #1                  // Field java/lang/System.out:Ljava/io/PrintStream;
      22: ldc           #6                  // String after
      24: invokevirtual #3                  // Method java/io/PrintStream.println:(Ljava/lang/String;)V
      27: aload         4
      29: areturn

  public ind.lw.java.dynamicproxy.TargetProxy(java.lang.Object);
    Code:
       0: aload_0
       1: invokespecial #7                  // Method java/lang/Object."<init>":()V
       4: aload_0
       5: aload_1
       6: putfield      #4                  // Field target:Ljava/lang/Object;
       9: return

  public java.lang.Object getProxy();
    Code:
       0: aload_0
       1: getfield      #4                  // Field target:Ljava/lang/Object;
       4: invokevirtual #8                  // Method java/lang/Object.getClass:()Ljava/lang/Class;
       7: invokevirtual #9                  // Method java/lang/Class.getClassLoader:()Ljava/lang/ClassLoader;
      10: aload_0
      11: getfield      #4                  // Field target:Ljava/lang/Object;
      14: invokevirtual #8                  // Method java/lang/Object.getClass:()Ljava/lang/Class;
      17: invokevirtual #10                 // Method java/lang/Class.getInterfaces:()[Ljava/lang/Class;
      20: aload_0
      21: invokestatic  #11                 // Method java/lang/reflect/Proxy.newProxyInstance:(Ljava/lang/ClassLoader;[Ljava/lang/Class;Ljava/lang/reflect/InvocationHandler;)Ljava/lang/Object;
      24: areturn
}
